cleaninty/__init__.py
cleaninty/__main__.py
cleaninty/_main.py
cleaninty/connection.py
cleaninty/exception.py
cleaninty/xml_helper.py
cleaninty/ctr/__init__.py
cleaninty/ctr/__main__.py
cleaninty/ctr/_env.py
cleaninty/ctr/_main.py
cleaninty/ctr/_py_ver_fixes.py
cleaninty/ctr/_sys_titles.py
cleaninty/ctr/act.py
cleaninty/ctr/apcert.py
cleaninty/ctr/boottimeemu.py
cleaninty/ctr/cdn.py
cleaninty/ctr/cdn_helpers.py
cleaninty/ctr/certificate.py
cleaninty/ctr/constants.py
cleaninty/ctr/digitalsignature.py
cleaninty/ctr/environment.py
cleaninty/ctr/exception.py
cleaninty/ctr/keys.py
cleaninty/ctr/lfcs.py
cleaninty/ctr/movablesed.py
cleaninty/ctr/ninja.py
cleaninty/ctr/otp.py
cleaninty/ctr/regionaldata.py
cleaninty/ctr/secureinfo.py
cleaninty/ctr/simpledevice.py
cleaninty/ctr/ticket.py
cleaninty/ctr/title.py
cleaninty/ctr/tmd.py
cleaninty/ctr/soap/__init__.py
cleaninty/ctr/soap/_common_parsers.py
cleaninty/ctr/soap/cas.py
cleaninty/ctr/soap/ecs.py
cleaninty/ctr/soap/exception.py
cleaninty/ctr/soap/helpers.py
cleaninty/ctr/soap/ias.py
cleaninty/ctr/soap/manager.py
cleaninty/ctr/soap/nus.py
cleaninty/ctr/ssl/__init__.py
cleaninty/ctr/ssl/_ssl_certs.py
cleaninty/nintendowifi/__init__.py
cleaninty/nintendowifi/soapenvelopebase.py
cleaninty/nintendowifi/soapsessionmanager.py
cleaninty-0.1.3.dist-info/LICENSE.md
cleaninty-0.1.3.dist-info/METADATA
cleaninty-0.1.3.dist-info/WHEEL
cleaninty-0.1.3.dist-info/entry_points.txt
cleaninty-0.1.3.dist-info/top_level.txt
cleaninty-0.1.3.dist-info/RECORD
