Metadata-Version: 2.1
Name: cleaninty
Version: 0.1.3
Summary: Python tool to perform some Nintendo console client to server operations
Home-page: https://github.com/luigoalma/cleaninty
Author: Luis Marques
License: Unlicense
Classifier: License :: OSI Approved :: The Unlicense (Unlicense)
Classifier: Programming Language :: Python :: 3
Classifier: Programming Language :: Python :: 3.7
Classifier: Programming Language :: Python :: 3.8
Classifier: Programming Language :: Python :: 3.9
Classifier: Programming Language :: Python :: 3.10
Classifier: Programming Language :: Python :: 3.11
Requires-Python: >=3.7
License-File: LICENSE.md
Requires-Dist: pycurl (>=7.45.0)
Requires-Dist: cryptography (>=38.0.0)
Requires-Dist: defusedxml
